toolm/__init__.py
toolm/agent.py
toolm/config.py
toolm/exceptions.py
toolm/utils.py
toolm-0.1.1.dist-info/licenses/LICENSE
toolm-0.1.1.dist-info/METADATA
toolm-0.1.1.dist-info/WHEEL
toolm-0.1.1.dist-info/top_level.txt
toolm-0.1.1.dist-info/RECORD
